GUIA_09/pulsos.v
/**
 * @file pulsos.v
 * @author 784778 - Wallace Freitas Oliveira (https://github.com/Olivwallace)
 * @brief Guia 09 Geradores Pulsos - Arquitetura de Computadores I (PUC-Minas 1°/2023)
 * @date 02-04-2023
 */

//-------------------- GUIA_0901
 //Gerador de Pulso
module pulse(input clock, output sgn);
    reg sgn;

    always @(clock) begin
            sgn = 1'b1;
        #3  sgn = 1'b0;
        #3  sgn = 1'b1;
        #3  sgn = 1'b0;
    end

endmodule

//-------------------- GUIA_0902
//Gerador de Pulso A
module pulseA(input clock, output sgn);
    reg sgn;

    always @(clock) begin
            sgn = 1'b1;
        #4  sgn = 1'b0;
        #4  sgn = 1'b1;
        #4  sgn = 1'b0;
        #4  sgn = 1'b1;
        #4  sgn = 1'b0;
    end
endmodule

//Gerador de Pulso B
module pulseB(input clock, output sgn);
    reg sgn;

    always @(clock) begin
            sgn = 1'b1;
        #5  sgn = 1'b0;
    end
endmodule

//Gerador de Pulso C
module pulseC(input clock, output sgn);
    reg sgn;

    always @(clock) begin
            sgn = 1'b1;
        #15  sgn = 1'b0;
        #15  sgn = 1'b1;
    end
endmodule

//Gerador de Pulso D
module pulseD(input clock, output sgn);
    reg sgn;

    always @(clock) begin
            sgn = 1'b1;
        #20  sgn = 1'b0;
        #20  sgn = 1'b1;
        #20  sgn = 1'b0;
    end
endmodule

//-------------------- GUIA_0903
//Gerador de Pulso de 1 terco da frequencia
module pulse_1TF(input clock, output sgn);
    reg sgn;

    always @(clock) begin
            sgn = 1'b1;
        #8  sgn = 1'b0;
        #8  sgn = 1'b1;
        #8  sgn = 1'b0;
    end
endmodule

//-------------------- GUIA_0904
//Gerador de Pulso de 4 vezes a frequencia
module pulse_4F(input clock, output sgn);
    reg sgn;

    always @(clock) begin
            sgn = 1'b1;
        #6  sgn = 1'b0;
        #6  sgn = 1'b1;
        #6  sgn = 1'b0;
    end
endmodule

//-------------------- GUIA_0905
//Gerador de Pulso de 4 vezes a frequencia
module pulse_2UT(input clock, output sgn);
    reg sgn;

    always @(posedge clock) begin
        sgn = 1'b1;
        #12 sgn = 1'b1;
        #12 sgn = 1'b0; 
    end
endmodule

GUIA_09/uteis.v
/**
 * @file uteis.v
 * @author 784778 - Wallace Freitas Oliveira (https://github.com/Olivwallace)
 * @brief Guia 09 Uteis - Arquitetura de Computadores I (PUC-Minas 1°/2023)
 * @date 02-04-2023
 */

//Gerador de Trigger
module trigger(input clock, input key, output sgn);
    reg sgn;

    always @(posedge clock & key) begin
        #60 sgn = 1'b1;
        #60 sgn = 1'b0;
    end

endmodule

//Contador de ciclos de clock
module contador (input clock, output reg[4: 0] data = 4'b0);
    
    always @(negedge clock) begin
        data = data + 4'b1;
    end

endmodule

GUIA_09/clock.v
/**
 * @file clock.v
 * @author 784778 - Wallace Freitas Oliveira (https://github.com/Olivwallace)
 * @brief Guia 09 Gerador Clock - Arquitetura de Computadores I (PUC-Minas 1°/2023)
 * @date 02-04-2023
 */

 //Gerador de Clock
module clock(output clk);
    
    reg clk;
    
    initial begin
        clk = 1'b0;    
    end

    always begin
        #12 clk = ~clk;
    end

endmodule

GUIA_09/Guia_0902.v
/**
 * @file Guia_0902.v
 * @author 784778 - Wallace Freitas Oliveira (https://github.com/Olivwallace)
 * @brief Guia 09 Exercicio 02 - Arquitetura de Computadores I (PUC-Minas 1°/2023)
 * @date 02-04-2023
 */

/*
 02)  Projetar e descrever em Verilog módulos geradores de pulso (pulse) com períodos diferentes.
O nome do arquivo deverá ser Guia_0902.v.
Incluir previsão de testes e verificação da carta de tempo usando GTKWave.
*/

`include "clock.v"
`include "pulsos.v"
`include "uteis.v"

//Teste do Modulo
module Guia_0902;
    wire clock;
    wire [4: 0] count;
    clock clk(clock);
    contador COUNT(.clock(clock), .data(count));

    wire pulseA, pulseB, pulseC, pulseD;

    pulseA P1(clock, pulseA);
    pulseB P2(clock, pulseB);
    pulseC P3(clock, pulseC);
    pulseD P4(clock, pulseD);

    initial begin
        $dumpfile("Guia_0902.vcd");
        $dumpvars(1, clock, count, pulseA, pulseB, pulseC, pulseD);

        #376 $finish;
    end
endmodule

GUIA_09/Guia_0902.vcd
$date
	Sun Apr 02 23:31:24 2023
$end
$version
	Icarus Verilog
$end
$timescale
	1s
$end
$scope module Guia_0902 $end
$var wire 1 ! clock $end
$upscope $end
$scope module Guia_0902 $end
$var wire 5 " count [4:0] $end
$upscope $end
$scope module Guia_0902 $end
$var wire 1 # pulseA $end
$upscope $end
$scope module Guia_0902 $end
$var wire 1 $ pulseB $end
$upscope $end
$scope module Guia_0902 $end
$var wire 1 % pulseC $end
$upscope $end
$scope module Guia_0902 $end
$var wire 1 & pulseD $end
$upscope $end
$enddefinitions $end
$comment Show the parameter values. $end
$dumpall
$end
#0
$dumpvars
1&
1%
1$
1#
b0 "
0!
$end
#4
0#
#5
0$
#8
1#
#12
1$
0#
1!
#15
0%
#16
1#
#17
0$
#20
0#
0&
#24
b1 "
1$
1#
0!
#28
0#
#29
0$
#30
1%
#32
1#
#36
1$
0#
1!
#40
1#
1&
#41
0$
#44
0#
#48
b10 "
1$
1#
0!
#51
0%
#52
0#
#53
0$
#56
1#
#60
1$
0#
1!
1&
#64
1#
#65
0$
#66
1%
#68
0#
#72
b11 "
1$
1#
0!
#76
0#
#77
0$
#80
1#
0&
#84
1$
0#
1!
#87
0%
#88
1#
#89
0$
#92
0#
#96
b100 "
1$
1#
0!
#100
0#
1&
#101
0$
#102
1%
#104
1#
#108
1$
0#
1!
#112
1#
#113
0$
#116
0#
#120
b101 "
1$
1#
0!
1&
#123
0%
#124
0#
#125
0$
#128
1#
#132
1$
0#
1!
#136
1#
#137
0$
#138
1%
#140
0#
0&
#144
b110 "
1$
1#
0!
#148
0#
#149
0$
#152
1#
#156
1$
0#
1!
#159
0%
#160
1#
1&
#161
0$
#164
0#
#168
b111 "
1$
1#
0!
#172
0#
#173
0$
#174
1%
#176
1#
#180
1$
0#
1!
1&
#184
1#
#185
0$
#188
0#
#192
b1000 "
1$
1#
0!
#195
0%
#196
0#
#197
0$
#200
1#
0&
#204
1$
0#
1!
#208
1#
#209
0$
#210
1%
#212
0#
#216
b1001 "
1$
1#
0!
#220
0#
1&
#221
0$
#224
1#
#228
1$
0#
1!
#231
0%
#232
1#
#233
0$
#236
0#
#240
b1010 "
1$
1#
0!
1&
#244
0#
#245
0$
#246
1%
#248
1#
#252
1$
0#
1!
#256
1#
#257
0$
#260
0#
0&
#264
b1011 "
1$
1#
0!
#267
0%
#268
0#
#269
0$
#272
1#
#276
1$
0#
1!
#280
1#
1&
#281
0$
#282
1%
#284
0#
#288
b1100 "
1$
1#
0!
#292
0#
#293
0$
#296
1#
#300
1$
0#
1!
1&
#303
0%
#304
1#
#305
0$
#308
0#
#312
b1101 "
1$
1#
0!
#316
0#
#317
0$
#318
1%
#320
1#
0&
#324
1$
0#
1!
#328
1#
#329
0$
#332
0#
#336
b1110 "
1$
1#
0!
#339
0%
#340
0#
1&
#341
0$
#344
1#
#348
1$
0#
1!
#352
1#
#353
0$
#354
1%
#356
0#
#360
b1111 "
1$
1#
0!
1&
#364
0#
#365
0$
#368
1#
#372
1$
0#
1!
#375
0%
#376
1#
