GUIA_09/pulsos.v
/**
 * @file pulsos.v
 * @author 784778 - Wallace Freitas Oliveira (https://github.com/Olivwallace)
 * @brief Guia 09 Geradores Pulsos - Arquitetura de Computadores I (PUC-Minas 1°/2023)
 * @date 02-04-2023
 */

//-------------------- GUIA_0901
 //Gerador de Pulso
module pulse(input clock, output sgn);
    reg sgn;

    always @(clock) begin
            sgn = 1'b1;
        #3  sgn = 1'b0;
        #3  sgn = 1'b1;
        #3  sgn = 1'b0;
    end

endmodule

//-------------------- GUIA_0902
//Gerador de Pulso A
module pulseA(input clock, output sgn);
    reg sgn;

    always @(clock) begin
            sgn = 1'b1;
        #4  sgn = 1'b0;
        #4  sgn = 1'b1;
        #4  sgn = 1'b0;
        #4  sgn = 1'b1;
        #4  sgn = 1'b0;
    end
endmodule

//Gerador de Pulso B
module pulseB(input clock, output sgn);
    reg sgn;

    always @(clock) begin
            sgn = 1'b1;
        #5  sgn = 1'b0;
    end
endmodule

//Gerador de Pulso C
module pulseC(input clock, output sgn);
    reg sgn;

    always @(clock) begin
            sgn = 1'b1;
        #15  sgn = 1'b0;
        #15  sgn = 1'b1;
    end
endmodule

//Gerador de Pulso D
module pulseD(input clock, output sgn);
    reg sgn;

    always @(clock) begin
            sgn = 1'b1;
        #20  sgn = 1'b0;
        #20  sgn = 1'b1;
        #20  sgn = 1'b0;
    end
endmodule

//-------------------- GUIA_0903
//Gerador de Pulso de 1 terco da frequencia
module pulse_1TF(input clock, output sgn);
    reg sgn;

    always @(clock) begin
            sgn = 1'b1;
        #8  sgn = 1'b0;
        #8  sgn = 1'b1;
        #8  sgn = 1'b0;
    end
endmodule

//-------------------- GUIA_0904
//Gerador de Pulso de 4 vezes a frequencia
module pulse_4F(input clock, output sgn);
    reg sgn;

    always @(clock) begin
            sgn = 1'b1;
        #6  sgn = 1'b0;
        #6  sgn = 1'b1;
        #6  sgn = 1'b0;
    end
endmodule

//-------------------- GUIA_0905
//Gerador de Pulso de 4 vezes a frequencia
module pulse_2UT(input clock, output sgn);
    reg sgn;

    always @(posedge clock) begin
        sgn = 1'b1;
        #12 sgn = 1'b1;
        #12 sgn = 1'b0; 
    end
endmodule

GUIA_09/uteis.v
/**
 * @file uteis.v
 * @author 784778 - Wallace Freitas Oliveira (https://github.com/Olivwallace)
 * @brief Guia 09 Uteis - Arquitetura de Computadores I (PUC-Minas 1°/2023)
 * @date 02-04-2023
 */

//Gerador de Trigger
module trigger(input clock, input key, output sgn);
    reg sgn;

    always @(posedge clock & key) begin
        #60 sgn = 1'b1;
        #60 sgn = 1'b0;
    end

endmodule

//Contador de ciclos de clock
module contador (input clock, output reg[4: 0] data = 4'b0);
    
    always @(negedge clock) begin
        data = data + 4'b1;
    end

endmodule

GUIA_09/clock.v
/**
 * @file clock.v
 * @author 784778 - Wallace Freitas Oliveira (https://github.com/Olivwallace)
 * @brief Guia 09 Gerador Clock - Arquitetura de Computadores I (PUC-Minas 1°/2023)
 * @date 02-04-2023
 */

 //Gerador de Clock
module clock(output clk);
    
    reg clk;
    
    initial begin
        clk = 1'b0;    
    end

    always begin
        #12 clk = ~clk;
    end

endmodule

GUIA_09/Guia_0905.v
/**
 * @file Guia_0905.v
 * @author 784778 - Wallace Freitas Oliveira (https://github.com/Olivwallace)
 * @brief Guia 09 Exercicio 05 - Arquitetura de Computadores I (PUC-Minas 1°/2023)
 * @date 02-04-2023
 */

/*
05) Projetar e descrever em Verilog um módulo gerador de pulso (pulse) com marcação igual
a 2 unidades de tempo, sincronizado com a borda de subida do gerador do Guia_09001.v.
O nome do arquivo deverá ser Guia_0905.v.
Incluir previsão de testes e verificação da carta de tempo usando GTKWave.
DICA: Usar always @(posedge clk).

*/

`include "clock.v"
`include "pulsos.v"
`include "uteis.v"

//Teste do Modulo
module Guia_0905;
    wire clock;
    wire [4: 0] count;
    clock clk(clock);
    contador COUNT(.clock(clock), .data(count));

    wire pulseA;
    pulse_2UT P1(clock, pulseA);

    initial begin
        $dumpfile("Guia_0905.vcd");
        $dumpvars(1, clock, count, pulseA);

        #376 $finish;
    end
endmodule

GUIA_09/Guia_0905.vcd
$date
	Sun Apr 02 23:51:40 2023
$end
$version
	Icarus Verilog
$end
$timescale
	1s
$end
$scope module Guia_0905 $end
$var wire 1 ! clock $end
$upscope $end
$scope module Guia_0905 $end
$var wire 5 " count [4:0] $end
$upscope $end
$scope module Guia_0905 $end
$var wire 1 # pulseA $end
$upscope $end
$enddefinitions $end
$comment Show the parameter values. $end
$dumpall
$end
#0
$dumpvars
x#
b0 "
0!
$end
#12
1#
1!
#24
b1 "
0!
#36
0#
1!
#48
b10 "
0!
#60
1#
1!
#72
b11 "
0!
#84
0#
1!
#96
b100 "
0!
#108
1#
1!
#120
b101 "
0!
#132
0#
1!
#144
b110 "
0!
#156
1#
1!
#168
b111 "
0!
#180
0#
1!
#192
b1000 "
0!
#204
1#
1!
#216
b1001 "
0!
#228
0#
1!
#240
b1010 "
0!
#252
1#
1!
#264
b1011 "
0!
#276
0#
1!
#288
b1100 "
0!
#300
1#
1!
#312
b1101 "
0!
#324
0#
1!
#336
b1110 "
0!
#348
1#
1!
#360
b1111 "
0!
#372
0#
1!
